wtpython/__init__.py
wtpython/__main__.py
wtpython/backends/__init__.py
wtpython/backends/cache.py
wtpython/backends/search_engine.py
wtpython/backends/stackoverflow.py
wtpython/backends/trace.py
wtpython/displays/__init__.py
wtpython/displays/no_display.py
wtpython/displays/textual_display.py
wtpython/exceptions.py
wtpython/formatters.py
wtpython/settings.py
wtpython-0.1.0.dist-info/entry_points.txt
wtpython-0.1.0.dist-info/LICENSE
wtpython-0.1.0.dist-info/WHEEL
wtpython-0.1.0.dist-info/METADATA
wtpython-0.1.0.dist-info/RECORD
