Metadata-Version: 2.1
Name: wtpython
Version: 0.1.0
Summary: A TUI that interactively helps you solve errors that might arise in your code.
Home-page: https://pypi.org/project/wtpython/
License: MIT
Author: Ethan Henry
Author-email: ethanparkerhenry@gmail.com
Requires-Python: >=3.7,<4.0
Classifier: Development Status :: 3 - Alpha
Classifier: Environment :: Console
Classifier: Intended Audience :: Developers
Classifier: License :: OSI Approved :: MIT License
Classifier: Programming Language :: Python :: 3
Classifier: Programming Language :: Python :: 3 :: Only
Classifier: Programming Language :: Python :: 3.10
Classifier: Programming Language :: Python :: 3.7
Classifier: Programming Language :: Python :: 3.8
Classifier: Programming Language :: Python :: 3.9
Classifier: Programming Language :: Python :: Implementation :: CPython
Provides-Extra: dev
Provides-Extra: test
Requires-Dist: markdownify (==0.9.2)
Requires-Dist: parse (==1.19.0)
Requires-Dist: pyperclip (==1.8.2)
Requires-Dist: requests (==2.25.1)
Requires-Dist: requests-cache (==0.7.1)
Requires-Dist: rich (==10.7.0)
Requires-Dist: textual (==0.1.9)
Requires-Dist: toml (==0.10.2)
Project-URL: Bug Tracker, https://github.com/what-the-python/wtpython/issues
Project-URL: Repository, https://github.com/what-the-python/wtpython
